[
  {
    "slug": "michael-jordan",
    "name": "Michael Jordan",
    "headline": "The Airness defined competitive fire with iconic finishes and relentless defense.",
    "positions": ["SG"],
    "era": "1980s-1990s",
    "active": false,
    "years": "1984-2003",
    "teams": ["CHI", "WAS"],
    "height": "6'6\"",
    "weight": 216,
    "birthDate": "1963-02-17",
    "numbers": [23, 45],
    "achievements": ["6x NBA Champion", "5x MVP", "10x Scoring Champ"],
    "image": "/images/players/michael-jordan.svg",
    "thumbnail": "/images/players/michael-jordan.svg",
    "heroQuote": "I've failed over and over and over again in my life. And that is why I succeed.",
    "heroAttribution": "Michael Jordan"
  },
  {
    "slug": "lebron-james",
    "name": "LeBron James",
    "headline": "Generational playmaker blending power, vision, and longevity across eras.",
    "positions": ["SF", "PF"],
    "era": "2000s-2020s",
    "active": true,
    "years": "2003-Present",
    "teams": ["CLE", "MIA", "LAL"],
    "height": "6'9\"",
    "weight": 250,
    "birthDate": "1984-12-30",
    "numbers": [6, 23],
    "achievements": ["4x NBA Champion", "4x MVP", "19x All-Star"],
    "image": "/images/players/lebron-james.svg",
    "thumbnail": "/images/players/lebron-james.svg",
    "heroQuote": "You have to be able to accept failure to get better.",
    "heroAttribution": "LeBron James"
  },
  {
    "slug": "kareem-abdul-jabbar",
    "name": "Kareem Abdul-Jabbar",
    "headline": "The skyhook artist who set the standard for sustained dominance.",
    "positions": ["C"],
    "era": "1970s-1980s",
    "active": false,
    "years": "1969-1989",
    "teams": ["MIL", "LAL"],
    "height": "7'2\"",
    "weight": 225,
    "birthDate": "1947-04-16",
    "numbers": [33],
    "achievements": ["6x NBA Champion", "6x MVP", "19x All-Star"],
    "image": "/images/players/kareem-abdul-jabbar.svg",
    "thumbnail": "/images/players/kareem-abdul-jabbar.svg",
    "heroQuote": "You can’t win unless you learn how to lose.",
    "heroAttribution": "Kareem Abdul-Jabbar"
  },
  {
    "slug": "magic-johnson",
    "name": "Magic Johnson",
    "headline": "Joyous floor general whose flair redefined Showtime basketball.",
    "positions": ["PG"],
    "era": "1980s",
    "active": false,
    "years": "1979-1996",
    "teams": ["LAL"],
    "height": "6'9\"",
    "weight": 220,
    "birthDate": "1959-08-14",
    "numbers": [32],
    "achievements": ["5x NBA Champion", "3x MVP", "12x All-Star"],
    "image": "/images/players/magic-johnson.svg",
    "thumbnail": "/images/players/magic-johnson.svg",
    "heroQuote": "All kids need is a little help, a little hope, and somebody who believes in them.",
    "heroAttribution": "Magic Johnson"
  },
  {
    "slug": "larry-bird",
    "name": "Larry Bird",
    "headline": "Sharpshooting forward marrying court vision with relentless competitiveness.",
    "positions": ["SF", "PF"],
    "era": "1980s",
    "active": false,
    "years": "1979-1992",
    "teams": ["BOS"],
    "height": "6'9\"",
    "weight": 220,
    "birthDate": "1956-12-07",
    "numbers": [33],
    "achievements": ["3x NBA Champion", "3x MVP", "12x All-Star"],
    "image": "/images/players/larry-bird.svg",
    "thumbnail": "/images/players/larry-bird.svg",
    "heroQuote": "Push yourself again and again. Don’t give an inch until the final buzzer sounds.",
    "heroAttribution": "Larry Bird"
  },
  {
    "slug": "bill-russell",
    "name": "Bill Russell",
    "headline": "The defensive anchor who turned winning into a habit and a legacy.",
    "positions": ["C"],
    "era": "1950s-1960s",
    "active": false,
    "years": "1956-1969",
    "teams": ["BOS"],
    "height": "6'10\"",
    "weight": 215,
    "birthDate": "1934-02-12",
    "numbers": [6],
    "achievements": ["11x NBA Champion", "5x MVP", "12x All-Star"],
    "image": "/images/players/bill-russell.svg",
    "thumbnail": "/images/players/bill-russell.svg",
    "heroQuote": "Commitment separates those who live their dreams from those who live their lives regretting the opportunities they have squandered.",
    "heroAttribution": "Bill Russell"
  }
]
